LICENSE
README.md
setup.py
wrenchbox/__init__.py
wrenchbox/alert.py
wrenchbox/config.py
wrenchbox/database.py
wrenchbox/datetime.py
wrenchbox/dict.py
wrenchbox/io.py
wrenchbox/list.py
wrenchbox/logging.py
wrenchbox/number.py
wrenchbox/object.py
wrenchbox/snowflake.py
wrenchbox/string.py
wrenchbox/text.py
wrenchbox/thread.py
wrenchbox.egg-info/PKG-INFO
wrenchbox.egg-info/SOURCES.txt
wrenchbox.egg-info/dependency_links.txt
wrenchbox.egg-info/requires.txt
wrenchbox.egg-info/top_level.txt