Metadata-Version: 2.1
Name: wrenchbox
Version: 1.12.27
Summary: Wrenchbox
Home-page: https://github.com/valency/wrenchbox
Author: Ye Ding
Author-email: guiewy@gmail.com
License: UNKNOWN
Keywords: toolbox,tools
Platform: UNKNOWN
License-File: LICENSE
